{
	"textures": {
		"0": "animated_java:item/fnaf_freddy/freddy_fazbear_v2"
	},
	"elements": [
		{
			"from": [
				7.25,
				7.25,
				7.25
			],
			"to": [
				8.75,
				8.75,
				8.75
			],
			"faces": {
				"north": {
					"uv": [
						0.25,
						10.875,
						0.5,
						11.125
					],
					"texture": "#0"
				},
				"east": {
					"uv": [
						0,
						10.875,
						0.25,
						11.125
					],
					"texture": "#0"
				},
				"south": {
					"uv": [
						0.75,
						10.875,
						1,
						11.125
					],
					"texture": "#0"
				},
				"west": {
					"uv": [
						0.5,
						10.875,
						0.75,
						11.125
					],
					"texture": "#0"
				},
				"up": {
					"uv": [
						0.5,
						10.875,
						0.25,
						10.625
					],
					"texture": "#0"
				},
				"down": {
					"uv": [
						0.75,
						10.625,
						0.5,
						10.875
					],
					"texture": "#0"
				}
			}
		}
	],
	"display": {
		"head": {
			"rotation": [
				0,
				180,
				0
			]
		}
	}
}