{
	"textures": {
		"0": "minecraft:custom/huggy_wuggy_bd"
	},
	"elements": [
		{
			"from": [
				6,
				4,
				6
			],
			"to": [
				10,
				8,
				10
			],
			"faces": {
				"north": {
					"uv": [
						4.108108108108108,
						8.756756756756756,
						4.54054054054054,
						9.18918918918919
					],
					"texture": "#0"
				},
				"east": {
					"uv": [
						3.675675675675676,
						8.756756756756756,
						4.108108108108108,
						9.18918918918919
					],
					"texture": "#0"
				},
				"south": {
					"uv": [
						4.972972972972973,
						8.756756756756756,
						5.405405405405405,
						9.18918918918919
					],
					"texture": "#0"
				},
				"west": {
					"uv": [
						4.54054054054054,
						8.756756756756756,
						4.972972972972973,
						9.18918918918919
					],
					"texture": "#0"
				},
				"up": {
					"uv": [
						4.54054054054054,
						8.756756756756756,
						4.108108108108108,
						8.324324324324325
					],
					"texture": "#0"
				},
				"down": {
					"uv": [
						4.972972972972973,
						8.324324324324325,
						4.54054054054054,
						8.756756756756756
					],
					"texture": "#0"
				}
			}
		}
	],
	"display": {
		"head": {
			"rotation": [
				0,
				180,
				0
			]
		}
	}
}